{
  "summary": {
    "total_flips": 353,
    "total_investors": 18,
    "total_profit": 40915126.0,
    "avg_roi": 77.30959180243582
  },
  "top_investors": [
    {
      "investor_name": "Georgia Property Investors",
      "total_flips": 28,
      "total_profit": 3346431.0,
      "avg_profit_per_flip": 119515.39285714286,
      "avg_hold_days": 82.85714285714286,
      "avg_roi": 100.0
    },
    {
      "investor_name": "Capital Flip Group",
      "total_flips": 27,
      "total_profit": 3175598.0,
      "avg_profit_per_flip": 117614.74074074074,
      "avg_hold_days": 82.70370370370371,
      "avg_roi": 100.0
    },
    {
      "investor_name": "Georgia Renovation Group",
      "total_flips": 24,
      "total_profit": 2881428.0,
      "avg_profit_per_flip": 120059.5,
      "avg_hold_days": 71.41666666666667,
      "avg_roi": 100.0
    },
    {
      "investor_name": "Property Solutions GA",
      "total_flips": 23,
      "total_profit": 2606048.0,
      "avg_profit_per_flip": 113306.43478260869,
      "avg_hold_days": 75.91304347826087,
      "avg_roi": 100.0
    },
    {
      "investor_name": "Peachtree RE Group",
      "total_flips": 22,
      "total_profit": 2397618.0,
      "avg_profit_per_flip": 108982.63636363637,
      "avg_hold_days": 85.95454545454545,
      "avg_roi": 100.0
    },
    {
      "investor_name": "Atlanta Capital Partners",
      "total_flips": 20,
      "total_profit": 2395986.0,
      "avg_profit_per_flip": 119799.3,
      "avg_hold_days": 98.95,
      "avg_roi": 100.0
    },
    {
      "investor_name": "Residential Ventures",
      "total_flips": 20,
      "total_profit": 2102646.0,
      "avg_profit_per_flip": 105132.3,
      "avg_hold_days": 85.6,
      "avg_roi": 100.0
    },
    {
      "investor_name": "Southern Holdings Inc",
      "total_flips": 20,
      "total_profit": 2317409.0,
      "avg_profit_per_flip": 115870.45,
      "avg_hold_days": 83.3,
      "avg_roi": 100.0
    },
    {
      "investor_name": "Investor Collective",
      "total_flips": 20,
      "total_profit": 2470783.0,
      "avg_profit_per_flip": 123539.15,
      "avg_hold_days": 81.9,
      "avg_roi": 100.0
    },
    {
      "investor_name": "Atlanta Flip Masters LLC",
      "total_flips": 19,
      "total_profit": 2227604.0,
      "avg_profit_per_flip": 117242.31578947368,
      "avg_hold_days": 81.52631578947368,
      "avg_roi": 100.0
    }
  ],
  "recent_flips": [
    {
      "property_id": "APP000001",
      "address": "9191 Elm Dr, Appling, GA 30011",
      "buy_date": "2025-08-28",
      "buy_price": 155225.0,
      "buyer": "Metro Atlanta Investments",
      "sell_date": "2025-12-08",
      "sell_price": 305169.0,
      "seller": "Metro Atlanta Investments",
      "hold_days": 102,
      "profit": 149944.0,
      "roi": 96.59784184248672,
      "county": "Appling County"
    },
    {
      "property_id": "APP000008",
      "address": "9049 Lincoln Rd, Appling, GA 30073",
      "buy_date": "2025-09-02",
      "buy_price": 140747.0,
      "buyer": "Quick Turn Properties",
      "sell_date": "2025-10-29",
      "sell_price": 278112.0,
      "seller": "Quick Turn Properties",
      "hold_days": 57,
      "profit": 137365.0,
      "roi": 97.59710686551045,
      "county": "Appling County"
    },
    {
      "property_id": "APP000015",
      "address": "2044 Oak Way, Appling, GA 30086",
      "buy_date": "2025-11-26",
      "buy_price": 81691.0,
      "buyer": "Capital Flip Group",
      "sell_date": "2026-01-17",
      "sell_price": 209895.0,
      "seller": "Capital Flip Group",
      "hold_days": 52,
      "profit": 128204.0,
      "roi": 156.93772875836996,
      "county": "Appling County"
    },
    {
      "property_id": "APP000016",
      "address": "256 Sugarloaf Way, Appling, GA 30079",
      "buy_date": "2025-10-03",
      "buy_price": 148981.0,
      "buyer": "Peach State Investments",
      "sell_date": "2025-12-07",
      "sell_price": 283315.0,
      "seller": "Peach State Investments",
      "hold_days": 65,
      "profit": 134334.0,
      "roi": 90.16854498224606,
      "county": "Appling County"
    },
    {
      "property_id": "APP000017",
      "address": "1429 Jefferson Ave, Appling, GA 30064",
      "buy_date": "2025-08-17",
      "buy_price": 161350.0,
      "buyer": "Residential Ventures",
      "sell_date": "2025-09-23",
      "sell_price": 274302.0,
      "seller": "Residential Ventures",
      "hold_days": 37,
      "profit": 112952.0,
      "roi": 70.00433839479393,
      "county": "Appling County"
    },
    {
      "property_id": "ATK000001",
      "address": "1646 Sugarloaf Rd, Atkinson, GA 30042",
      "buy_date": "2025-09-30",
      "buy_price": 206820.0,
      "buyer": "Georgia Property Investors",
      "sell_date": "2025-11-28",
      "sell_price": 301181.0,
      "seller": "Georgia Property Investors",
      "hold_days": 59,
      "profit": 94361.0,
      "roi": 45.62469780485446,
      "county": "Atkinson County"
    },
    {
      "property_id": "ATK000004",
      "address": "2966 Memorial Dr, Atkinson, GA 30075",
      "buy_date": "2025-09-28",
      "buy_price": 160407.0,
      "buyer": "Capital Flip Group",
      "sell_date": "2025-12-23",
      "sell_price": 284607.0,
      "seller": "Capital Flip Group",
      "hold_days": 86,
      "profit": 124200.0,
      "roi": 77.4280424171015,
      "county": "Atkinson County"
    },
    {
      "property_id": "ATK000005",
      "address": "9398 Broad Dr, Atkinson, GA 30096",
      "buy_date": "2025-10-08",
      "buy_price": 108524.0,
      "buyer": "Investor Collective",
      "sell_date": "2025-11-21",
      "sell_price": 204838.0,
      "seller": "Investor Collective",
      "hold_days": 44,
      "profit": 96314.0,
      "roi": 88.74903247207992,
      "county": "Atkinson County"
    },
    {
      "property_id": "BAC000009",
      "address": "8753 Washington Blvd, Bacon, GA 30074",
      "buy_date": "2025-09-09",
      "buy_price": 181548.0,
      "buyer": "Atlanta Capital Partners",
      "sell_date": "2025-11-02",
      "sell_price": 296993.0,
      "seller": "Atlanta Capital Partners",
      "hold_days": 54,
      "profit": 115445.0,
      "roi": 63.58924361601339,
      "county": "Bacon County"
    },
    {
      "property_id": "BAC000011",
      "address": "6706 Washington Blvd, Bacon, GA 30079",
      "buy_date": "2025-11-17",
      "buy_price": 99494.0,
      "buyer": "Georgia Home Solutions",
      "sell_date": "2025-12-17",
      "sell_price": 183049.0,
      "seller": "Georgia Home Solutions",
      "hold_days": 30,
      "profit": 83555.0,
      "roi": 83.97993848875309,
      "county": "Bacon County"
    },
    {
      "property_id": "BAC000017",
      "address": "7023 Oak Pkwy, Bacon, GA 30067",
      "buy_date": "2025-09-20",
      "buy_price": 239860.0,
      "buyer": "Renovation Experts",
      "sell_date": "2025-12-12",
      "sell_price": 354240.0,
      "seller": "Renovation Experts",
      "hold_days": 83,
      "profit": 114380.0,
      "roi": 47.68615025431502,
      "county": "Bacon County"
    },
    {
      "property_id": "BAK000002",
      "address": "353 Lincoln Dr, Baker, GA 30038",
      "buy_date": "2025-12-08",
      "buy_price": 126044.0,
      "buyer": "Peachtree RE Group",
      "sell_date": "2026-01-26",
      "sell_price": 206808.0,
      "seller": "Peachtree RE Group",
      "hold_days": 49,
      "profit": 80764.0,
      "roi": 64.07603693948145,
      "county": "Baker County"
    },
    {
      "property_id": "BAL000012",
      "address": "9352 Barrett Ave, Baldwin, GA 30096",
      "buy_date": "2025-08-21",
      "buy_price": 245100.0,
      "buyer": "Atlanta Flip Masters LLC",
      "sell_date": "2026-01-28",
      "sell_price": 357763.0,
      "seller": "Atlanta Flip Masters LLC",
      "hold_days": 160,
      "profit": 112663.0,
      "roi": 45.966136270909836,
      "county": "Baldwin County"
    },
    {
      "property_id": "BAL000016",
      "address": "3322 Barrett Way, Baldwin, GA 30049",
      "buy_date": "2025-08-08",
      "buy_price": 142876.0,
      "buyer": "Peach State Investments",
      "sell_date": "2025-11-24",
      "sell_price": 258264.0,
      "seller": "Peach State Investments",
      "hold_days": 108,
      "profit": 115388.0,
      "roi": 80.76093955597861,
      "county": "Baldwin County"
    },
    {
      "property_id": "BAL000020",
      "address": "1463 Peachtree Rd, Baldwin, GA 30093",
      "buy_date": "2025-08-17",
      "buy_price": 99690.0,
      "buyer": "Southern Holdings Inc",
      "sell_date": "2026-01-29",
      "sell_price": 192802.0,
      "seller": "Southern Holdings Inc",
      "hold_days": 165,
      "profit": 93112.0,
      "roi": 93.40154478884543,
      "county": "Baldwin County"
    },
    {
      "property_id": "BAN000015",
      "address": "3606 Elm Way, Banks, GA 30025",
      "buy_date": "2025-11-20",
      "buy_price": 135858.0,
      "buyer": "Atlanta Flip Masters LLC",
      "sell_date": "2026-01-21",
      "sell_price": 256185.0,
      "seller": "Atlanta Flip Masters LLC",
      "hold_days": 62,
      "profit": 120327.0,
      "roi": 88.56821092611403,
      "county": "Banks County"
    },
    {
      "property_id": "BAN000018",
      "address": "8922 Washington Ave, Banks, GA 30098",
      "buy_date": "2025-11-22",
      "buy_price": 217478.0,
      "buyer": "Georgia Renovation Group",
      "sell_date": "2026-01-04",
      "sell_price": 297721.0,
      "seller": "Georgia Renovation Group",
      "hold_days": 43,
      "profit": 80243.0,
      "roi": 36.89706545029842,
      "county": "Banks County"
    },
    {
      "property_id": "BAR000002",
      "address": "3354 Memorial Dr, Barrow, GA 30044",
      "buy_date": "2025-12-11",
      "buy_price": 192853.0,
      "buyer": "Georgia Property Investors",
      "sell_date": "2026-01-27",
      "sell_price": 312625.0,
      "seller": "Georgia Property Investors",
      "hold_days": 47,
      "profit": 119772.0,
      "roi": 62.105334114584686,
      "county": "Barrow County"
    },
    {
      "property_id": "BAR000003",
      "address": "2551 Broad Dr, Bartow, GA 30072",
      "buy_date": "2025-08-17",
      "buy_price": 129094.0,
      "buyer": "Georgia Property Investors",
      "sell_date": "2026-01-25",
      "sell_price": 251103.0,
      "seller": "Georgia Property Investors",
      "hold_days": 161,
      "profit": 122009.0,
      "roi": 94.51175112708569,
      "county": "Bartow County"
    },
    {
      "property_id": "BAR000003",
      "address": "7272 Market Blvd, Barrow, GA 30067",
      "buy_date": "2025-11-12",
      "buy_price": 151659.0,
      "buyer": "Georgia Property Investors",
      "sell_date": "2026-01-25",
      "sell_price": 251103.0,
      "seller": "Georgia Property Investors",
      "hold_days": 74,
      "profit": 99444.0,
      "roi": 65.57078709473227,
      "county": "Barrow County"
    },
    {
      "property_id": "BAR000004",
      "address": "8380 Jefferson Dr, Barrow, GA 30086",
      "buy_date": "2025-08-04",
      "buy_price": 125689.0,
      "buyer": "Metro Atlanta Investments",
      "sell_date": "2026-01-27",
      "sell_price": 247797.0,
      "seller": "Metro Atlanta Investments",
      "hold_days": 176,
      "profit": 122108.0,
      "roi": 97.15090421596162,
      "county": "Barrow County"
    },
    {
      "property_id": "BAR000006",
      "address": "1449 Main St, Barrow, GA 30011",
      "buy_date": "2025-12-09",
      "buy_price": 140443.0,
      "buyer": "Residential Ventures",
      "sell_date": "2026-01-13",
      "sell_price": 252503.0,
      "seller": "Residential Ventures",
      "hold_days": 35,
      "profit": 112060.0,
      "roi": 79.79037759090876,
      "county": "Barrow County"
    },
    {
      "property_id": "BAR000010",
      "address": "346 Cedar Blvd, Barrow, GA 30035",
      "buy_date": "2025-09-15",
      "buy_price": 97453.0,
      "buyer": "Southern Holdings Inc",
      "sell_date": "2025-12-27",
      "sell_price": 237448.0,
      "seller": "Southern Holdings Inc",
      "hold_days": 103,
      "profit": 139995.0,
      "roi": 143.6538639138867,
      "county": "Barrow County"
    },
    {
      "property_id": "BEN000011",
      "address": "4594 Cedar Dr, Ben, GA 30050",
      "buy_date": "2025-09-11",
      "buy_price": 126146.0,
      "buyer": "Peach State Investments",
      "sell_date": "2025-12-01",
      "sell_price": 269197.0,
      "seller": "Peach State Investments",
      "hold_days": 81,
      "profit": 143051.0,
      "roi": 113.40113836348358,
      "county": "Ben Hill County"
    },
    {
      "property_id": "BEN000017",
      "address": "2239 Maple Way, Ben, GA 30075",
      "buy_date": "2025-10-28",
      "buy_price": 196235.0,
      "buyer": "Fix & Flip GA",
      "sell_date": "2025-11-28",
      "sell_price": 305013.0,
      "seller": "Fix & Flip GA",
      "hold_days": 31,
      "profit": 108778.0,
      "roi": 55.43251713506765,
      "county": "Ben Hill County"
    },
    {
      "property_id": "BEN000022",
      "address": "5633 Cedar Way, Ben, GA 30062",
      "buy_date": "2025-09-21",
      "buy_price": 137094.0,
      "buyer": "Urban Development LLC",
      "sell_date": "2026-01-04",
      "sell_price": 282264.0,
      "seller": "Urban Development LLC",
      "hold_days": 105,
      "profit": 145170.0,
      "roi": 105.89084861481903,
      "county": "Ben Hill County"
    },
    {
      "property_id": "BER000001",
      "address": "6598 Memorial Way, Berrien, GA 30087",
      "buy_date": "2025-08-17",
      "buy_price": 165454.0,
      "buyer": "Property Solutions GA",
      "sell_date": "2025-10-02",
      "sell_price": 313229.0,
      "seller": "Property Solutions GA",
      "hold_days": 46,
      "profit": 147775.0,
      "roi": 89.31485488413699,
      "county": "Berrien County"
    },
    {
      "property_id": "BER000009",
      "address": "4855 Washington Blvd, Berrien, GA 30063",
      "buy_date": "2025-12-15",
      "buy_price": 233871.0,
      "buyer": "Fix & Flip GA",
      "sell_date": "2026-01-23",
      "sell_price": 351122.0,
      "seller": "Fix & Flip GA",
      "hold_days": 39,
      "profit": 117251.0,
      "roi": 50.13490342966848,
      "county": "Berrien County"
    },
    {
      "property_id": "BER000013",
      "address": "6486 Market Ave, Berrien, GA 30099",
      "buy_date": "2025-08-21",
      "buy_price": 203080.0,
      "buyer": "Capital Flip Group",
      "sell_date": "2025-12-18",
      "sell_price": 292450.0,
      "seller": "Capital Flip Group",
      "hold_days": 119,
      "profit": 89370.0,
      "roi": 44.00728776836715,
      "county": "Berrien County"
    },
    {
      "property_id": "BIB000010",
      "address": "7068 Peachtree Dr, Bibb, GA 30095",
      "buy_date": "2025-08-13",
      "buy_price": 214419.0,
      "buyer": "Residential Ventures",
      "sell_date": "2025-12-03",
      "sell_price": 321833.0,
      "seller": "Residential Ventures",
      "hold_days": 112,
      "profit": 107414.0,
      "roi": 50.09537401069868,
      "county": "Bibb County"
    },
    {
      "property_id": "BIB000014",
      "address": "891 Jefferson Way, Bibb, GA 30061",
      "buy_date": "2025-10-25",
      "buy_price": 203315.0,
      "buyer": "Peach State Investments",
      "sell_date": "2025-12-01",
      "sell_price": 324731.0,
      "seller": "Peach State Investments",
      "hold_days": 37,
      "profit": 121416.0,
      "roi": 59.718171310528,
      "county": "Bibb County"
    },
    {
      "property_id": "BIB000020",
      "address": "8312 Sugarloaf St, Bibb, GA 30024",
      "buy_date": "2025-09-22",
      "buy_price": 114296.0,
      "buyer": "Capital Flip Group",
      "sell_date": "2025-11-30",
      "sell_price": 248080.0,
      "seller": "Capital Flip Group",
      "hold_days": 69,
      "profit": 133784.0,
      "roi": 117.05046545810877,
      "county": "Bibb County"
    },
    {
      "property_id": "BLE000005",
      "address": "6796 Cedar Blvd, Bleckley, GA 30012",
      "buy_date": "2025-08-03",
      "buy_price": 166115.0,
      "buyer": "Atlanta Capital Partners",
      "sell_date": "2025-11-30",
      "sell_price": 296673.0,
      "seller": "Atlanta Capital Partners",
      "hold_days": 119,
      "profit": 130558.0,
      "roi": 78.59494928212382,
      "county": "Bleckley County"
    },
    {
      "property_id": "BLE000007",
      "address": "4530 Jefferson Way, Bleckley, GA 30065",
      "buy_date": "2025-09-22",
      "buy_price": 191505.0,
      "buyer": "Renovation Experts",
      "sell_date": "2026-01-11",
      "sell_price": 295527.0,
      "seller": "Renovation Experts",
      "hold_days": 111,
      "profit": 104022.0,
      "roi": 54.31816401660531,
      "county": "Bleckley County"
    },
    {
      "property_id": "BLE000009",
      "address": "8787 Cedar Ave, Bleckley, GA 30012",
      "buy_date": "2025-10-07",
      "buy_price": 194452.0,
      "buyer": "Southern Holdings Inc",
      "sell_date": "2026-01-18",
      "sell_price": 337679.0,
      "seller": "Southern Holdings Inc",
      "hold_days": 103,
      "profit": 143227.0,
      "roi": 73.65673790961266,
      "county": "Bleckley County"
    },
    {
      "property_id": "BLE000012",
      "address": "6875 Maple Way, Bleckley, GA 30075",
      "buy_date": "2025-08-10",
      "buy_price": 134391.0,
      "buyer": "Atlanta Capital Partners",
      "sell_date": "2026-01-24",
      "sell_price": 254556.0,
      "seller": "Atlanta Capital Partners",
      "hold_days": 167,
      "profit": 120165.0,
      "roi": 89.4144697189544,
      "county": "Bleckley County"
    },
    {
      "property_id": "BLE000013",
      "address": "2638 Lincoln Way, Bleckley, GA 30053",
      "buy_date": "2025-09-17",
      "buy_price": 201971.0,
      "buyer": "Quick Turn Properties",
      "sell_date": "2026-01-03",
      "sell_price": 298428.0,
      "seller": "Quick Turn Properties",
      "hold_days": 108,
      "profit": 96457.0,
      "roi": 47.75784642349644,
      "county": "Bleckley County"
    },
    {
      "property_id": "BRA000015",
      "address": "4796 Cedar Way, Brantley, GA 30052",
      "buy_date": "2025-09-08",
      "buy_price": 139395.0,
      "buyer": "Quick Turn Properties",
      "sell_date": "2026-01-27",
      "sell_price": 288259.0,
      "seller": "Quick Turn Properties",
      "hold_days": 141,
      "profit": 148864.0,
      "roi": 106.79292657555865,
      "county": "Brantley County"
    },
    {
      "property_id": "BRO000009",
      "address": "8653 Oak Way, Brooks, GA 30021",
      "buy_date": "2025-09-24",
      "buy_price": 224076.0,
      "buyer": "Quick Turn Properties",
      "sell_date": "2025-11-26",
      "sell_price": 301607.0,
      "seller": "Quick Turn Properties",
      "hold_days": 63,
      "profit": 77531.0,
      "roi": 34.600314179117795,
      "county": "Brooks County"
    },
    {
      "property_id": "BRO000013",
      "address": "7262 Lincoln St, Brooks, GA 30044",
      "buy_date": "2025-12-20",
      "buy_price": 87552.0,
      "buyer": "Renovation Experts",
      "sell_date": "2026-01-30",
      "sell_price": 209730.0,
      "seller": "Renovation Experts",
      "hold_days": 41,
      "profit": 122178.0,
      "roi": 139.54906798245614,
      "county": "Brooks County"
    },
    {
      "property_id": "BRO000017",
      "address": "4142 Elm Blvd, Brooks, GA 30099",
      "buy_date": "2025-10-06",
      "buy_price": 175033.0,
      "buyer": "Metro Flip Team",
      "sell_date": "2025-12-26",
      "sell_price": 270996.0,
      "seller": "Metro Flip Team",
      "hold_days": 81,
      "profit": 95963.0,
      "roi": 54.825661446698625,
      "county": "Brooks County"
    },
    {
      "property_id": "BRY000009",
      "address": "8275 Broad Rd, Bryan, GA 30022",
      "buy_date": "2025-08-10",
      "buy_price": 175419.0,
      "buyer": "Metro Atlanta Investments",
      "sell_date": "2025-12-23",
      "sell_price": 314288.0,
      "seller": "Metro Atlanta Investments",
      "hold_days": 135,
      "profit": 138869.0,
      "roi": 79.16417263808367,
      "county": "Bryan County"
    },
    {
      "property_id": "BUL000004",
      "address": "4465 Maple Pkwy, Bulloch, GA 30029",
      "buy_date": "2025-08-16",
      "buy_price": 177793.0,
      "buyer": "Peach State Investments",
      "sell_date": "2026-01-22",
      "sell_price": 281457.0,
      "seller": "Peach State Investments",
      "hold_days": 159,
      "profit": 103664.0,
      "roi": 58.306007548103686,
      "county": "Bulloch County"
    },
    {
      "property_id": "BUL000006",
      "address": "6758 Washington St, Bulloch, GA 30023",
      "buy_date": "2025-09-06",
      "buy_price": 207097.0,
      "buyer": "Property Solutions GA",
      "sell_date": "2026-01-23",
      "sell_price": 327433.0,
      "seller": "Property Solutions GA",
      "hold_days": 139,
      "profit": 120336.0,
      "roi": 58.10610486873301,
      "county": "Bulloch County"
    },
    {
      "property_id": "BUL000014",
      "address": "9260 Jefferson Dr, Bulloch, GA 30075",
      "buy_date": "2025-09-25",
      "buy_price": 163209.0,
      "buyer": "Metro Atlanta Investments",
      "sell_date": "2025-11-15",
      "sell_price": 279534.0,
      "seller": "Metro Atlanta Investments",
      "hold_days": 51,
      "profit": 116325.0,
      "roi": 71.27364299762881,
      "county": "Bulloch County"
    },
    {
      "property_id": "BUR000018",
      "address": "8505 Broad Dr, Burke, GA 30023",
      "buy_date": "2025-11-20",
      "buy_price": 217972.0,
      "buyer": "Atlanta Flip Masters LLC",
      "sell_date": "2026-01-30",
      "sell_price": 342229.0,
      "seller": "Atlanta Flip Masters LLC",
      "hold_days": 71,
      "profit": 124257.0,
      "roi": 57.00594571779861,
      "county": "Burke County"
    },
    {
      "property_id": "BUT000001",
      "address": "1373 Oak Pkwy, Butts, GA 30059",
      "buy_date": "2025-10-30",
      "buy_price": 172063.0,
      "buyer": "Peachtree RE Group",
      "sell_date": "2025-12-20",
      "sell_price": 289134.0,
      "seller": "Peachtree RE Group",
      "hold_days": 51,
      "profit": 117071.0,
      "roi": 68.03961339741839,
      "county": "Butts County"
    },
    {
      "property_id": "BUT000002",
      "address": "7420 Sugarloaf St, Butts, GA 30094",
      "buy_date": "2025-08-08",
      "buy_price": 128032.0,
      "buyer": "Southern Holdings Inc",
      "sell_date": "2025-10-19",
      "sell_price": 240857.0,
      "seller": "Southern Holdings Inc",
      "hold_days": 72,
      "profit": 112825.0,
      "roi": 88.1225006248438,
      "county": "Butts County"
    },
    {
      "property_id": "BUT000014",
      "address": "1225 Washington Dr, Butts, GA 30045",
      "buy_date": "2025-10-18",
      "buy_price": 190785.0,
      "buyer": "Metro Flip Team",
      "sell_date": "2025-12-17",
      "sell_price": 310306.0,
      "seller": "Metro Flip Team",
      "hold_days": 60,
      "profit": 119521.0,
      "roi": 62.64695861834002,
      "county": "Butts County"
    },
    {
      "property_id": "CAL000006",
      "address": "9122 Maple Way, Calhoun, GA 30076",
      "buy_date": "2025-09-07",
      "buy_price": 222596.0,
      "buyer": "Peachtree RE Group",
      "sell_date": "2025-11-16",
      "sell_price": 356469.0,
      "seller": "Peachtree RE Group",
      "hold_days": 70,
      "profit": 133873.0,
      "roi": 60.141691674603315,
      "county": "Calhoun County"
    }
  ],
  "stats": {
    "total_flips_identified": 353,
    "total_investors": 18,
    "total_profit": 40915126.0,
    "avg_roi": 77.30959180243582,
    "last_updated": "2026-01-30",
    "by_county": {
      "Dawson County": 6,
      "Houston County": 6,
      "Appling County": 5,
      "Barrow County": 5,
      "Bleckley County": 5,
      "Jenkins County": 5,
      "Pulaski County": 5,
      "Spalding County": 5,
      "Warren County": 5,
      "Catoosa County": 4,
      "Chatham County": 4,
      "Elbert County": 4,
      "Gordon County": 4,
      "Hancock County": 4,
      "Johnson County": 4,
      "Jones County": 4,
      "Lamar County": 4,
      "Lumpkin County": 4,
      "Macon County": 4,
      "Madison County": 4,
      "Miller County": 4,
      "Murray County": 4,
      "Upson County": 4,
      "Ware County": 4,
      "White County": 4,
      "Atkinson County": 3,
      "Bacon County": 3,
      "Baldwin County": 3,
      "Ben Hill County": 3,
      "Berrien County": 3,
      "Bibb County": 3,
      "Brooks County": 3,
      "Bulloch County": 3,
      "Butts County": 3,
      "Calhoun County": 3,
      "Camden County": 3,
      "Chattahoochee County": 3,
      "Clarke County": 3,
      "Colquitt County": 3,
      "Columbia County": 3,
      "Crawford County": 3,
      "Emanuel County": 3,
      "Fayette County": 3,
      "Fulton County": 3,
      "Glynn County": 3,
      "Haralson County": 3,
      "Henry County": 3,
      "Jasper County": 3,
      "Long County": 3,
      "Marion County": 3,
      "Monroe County": 3,
      "Montgomery County": 3,
      "Paulding County": 3,
      "Pickens County": 3,
      "Putnam County": 3,
      "Quitman County": 3,
      "Rockdale County": 3,
      "Screven County": 3,
      "Sumter County": 3,
      "Taylor County": 3,
      "Twiggs County": 3,
      "Walton County": 3,
      "Webster County": 3,
      "Banks County": 2,
      "Chattooga County": 2,
      "Clay County": 2,
      "Clayton County": 2,
      "Clinch County": 2,
      "Decatur County": 2,
      "Dooly County": 2,
      "Echols County": 2,
      "Evans County": 2,
      "Franklin County": 2,
      "Gilmer County": 2,
      "Glascock County": 2,
      "Greene County": 2,
      "Habersham County": 2,
      "Irwin County": 2,
      "Jackson County": 2,
      "Jefferson County": 2,
      "Laurens County": 2,
      "Liberty County": 2,
      "Lincoln County": 2,
      "Meriwether County": 2,
      "Morgan County": 2,
      "Oconee County": 2,
      "Oglethorpe County": 2,
      "Peach County": 2,
      "Pike County": 2,
      "Polk County": 2,
      "Stephens County": 2,
      "Talbot County": 2,
      "Tattnall County": 2,
      "Terrell County": 2,
      "Thomas County": 2,
      "Tift County": 2,
      "Toombs County": 2,
      "Towns County": 2,
      "Troup County": 2,
      "Turner County": 2,
      "Union County": 2,
      "Walker County": 2,
      "Wheeler County": 2,
      "Whitfield County": 2,
      "Wilcox County": 2,
      "Wilkinson County": 2,
      "Baker County": 1,
      "Bartow County": 1,
      "Brantley County": 1,
      "Bryan County": 1,
      "Burke County": 1,
      "Candler County": 1,
      "Carroll County": 1,
      "Charlton County": 1,
      "Cobb County": 1,
      "Coffee County": 1,
      "Cook County": 1,
      "Coweta County": 1,
      "DeKalb County": 1,
      "Dodge County": 1,
      "Dougherty County": 1,
      "Douglas County": 1,
      "Early County": 1,
      "Effingham County": 1,
      "Fannin County": 1,
      "Floyd County": 1,
      "Forsyth County": 1,
      "Grady County": 1,
      "Gwinnett County": 1,
      "Hart County": 1,
      "Harris County": 1,
      "Heard County": 1,
      "Jeff Davis County": 1,
      "Lanier County": 1,
      "Lee County": 1,
      "Lowndes County": 1,
      "McIntosh County": 1,
      "Pierce County": 1,
      "Rabun County": 1,
      "Randolph County": 1,
      "Richmond County": 1,
      "Schley County": 1,
      "Seminole County": 1,
      "Stewart County": 1,
      "Washington County": 1,
      "Wayne County": 1,
      "Wilkes County": 1,
      "Worth County": 1
    },
    "profit_distribution": {
      "70k-100k": 81,
      "100k-130k": 165,
      "130k-160k": 107,
      "160k+": 0
    }
  }
}