{
  "summary": {
    "total_flips": 357,
    "total_investors": 18,
    "total_profit": 40807044.0,
    "avg_roi": 75.52652469450443
  },
  "top_investors": [
    {
      "investor_name": "Southern Holdings Inc",
      "total_flips": 26,
      "total_profit": 3085780.0,
      "avg_profit_per_flip": 118683.84615384616,
      "avg_hold_days": 70.15384615384616,
      "avg_roi": 100.0
    },
    {
      "investor_name": "Georgia Home Solutions",
      "total_flips": 25,
      "total_profit": 2874661.0,
      "avg_profit_per_flip": 114986.44,
      "avg_hold_days": 90.2,
      "avg_roi": 100.0
    },
    {
      "investor_name": "Property Solutions GA",
      "total_flips": 25,
      "total_profit": 2745252.0,
      "avg_profit_per_flip": 109810.08,
      "avg_hold_days": 72.8,
      "avg_roi": 100.0
    },
    {
      "investor_name": "Renovation Experts",
      "total_flips": 24,
      "total_profit": 2873051.0,
      "avg_profit_per_flip": 119710.45833333333,
      "avg_hold_days": 89.08333333333333,
      "avg_roi": 100.0
    },
    {
      "investor_name": "Georgia Renovation Group",
      "total_flips": 23,
      "total_profit": 2607264.0,
      "avg_profit_per_flip": 113359.30434782608,
      "avg_hold_days": 93.08695652173913,
      "avg_roi": 100.0
    },
    {
      "investor_name": "Georgia Property Investors",
      "total_flips": 23,
      "total_profit": 2799344.0,
      "avg_profit_per_flip": 121710.60869565218,
      "avg_hold_days": 74.08695652173913,
      "avg_roi": 100.0
    },
    {
      "investor_name": "Investor Collective",
      "total_flips": 22,
      "total_profit": 2453271.0,
      "avg_profit_per_flip": 111512.31818181818,
      "avg_hold_days": 77.13636363636364,
      "avg_roi": 100.0
    },
    {
      "investor_name": "Peachtree RE Group",
      "total_flips": 20,
      "total_profit": 2238053.0,
      "avg_profit_per_flip": 111902.65,
      "avg_hold_days": 78.4,
      "avg_roi": 100.0
    },
    {
      "investor_name": "Residential Ventures",
      "total_flips": 20,
      "total_profit": 2316580.0,
      "avg_profit_per_flip": 115829.0,
      "avg_hold_days": 66.35,
      "avg_roi": 100.0
    },
    {
      "investor_name": "Metro Atlanta Investments",
      "total_flips": 20,
      "total_profit": 2260557.0,
      "avg_profit_per_flip": 113027.85,
      "avg_hold_days": 67.0,
      "avg_roi": 100.0
    }
  ],
  "recent_flips": [
    {
      "property_id": "APP000006",
      "address": "1806 Memorial St, Appling, GA 30065",
      "buy_date": "2025-09-08",
      "buy_price": 92056.0,
      "buyer": "Southern Holdings Inc",
      "sell_date": "2025-11-17",
      "sell_price": 187497.0,
      "seller": "Southern Holdings Inc",
      "hold_days": 70,
      "profit": 95441.0,
      "roi": 103.67710958546972,
      "county": "Appling County"
    },
    {
      "property_id": "APP000009",
      "address": "8245 Cedar Ln, Appling, GA 30090",
      "buy_date": "2025-09-08",
      "buy_price": 85174.0,
      "buyer": "Residential Ventures",
      "sell_date": "2025-10-10",
      "sell_price": 186919.0,
      "seller": "Residential Ventures",
      "hold_days": 32,
      "profit": 101745.0,
      "roi": 119.45546763096719,
      "county": "Appling County"
    },
    {
      "property_id": "APP000011",
      "address": "3795 Cedar Blvd, Appling, GA 30040",
      "buy_date": "2025-11-19",
      "buy_price": 154834.0,
      "buyer": "Georgia Renovation Group",
      "sell_date": "2026-02-24",
      "sell_price": 292266.0,
      "seller": "Georgia Renovation Group",
      "hold_days": 97,
      "profit": 137432.0,
      "roi": 88.76086647635533,
      "county": "Appling County"
    },
    {
      "property_id": "APP000020",
      "address": "4759 Sugarloaf Rd, Appling, GA 30053",
      "buy_date": "2026-01-02",
      "buy_price": 82488.0,
      "buyer": "Peach State Investments",
      "sell_date": "2026-02-03",
      "sell_price": 227834.0,
      "seller": "Peach State Investments",
      "hold_days": 32,
      "profit": 145346.0,
      "roi": 176.2025991659393,
      "county": "Appling County"
    },
    {
      "property_id": "ATK000004",
      "address": "9077 Peachtree Rd, Atkinson, GA 30088",
      "buy_date": "2025-12-11",
      "buy_price": 81568.0,
      "buyer": "Investor Collective",
      "sell_date": "2026-01-30",
      "sell_price": 186635.0,
      "seller": "Investor Collective",
      "hold_days": 50,
      "profit": 105067.0,
      "roi": 128.80909180070617,
      "county": "Atkinson County"
    },
    {
      "property_id": "ATK000006",
      "address": "6346 Lincoln Dr, Atkinson, GA 30051",
      "buy_date": "2025-11-07",
      "buy_price": 233746.0,
      "buyer": "Georgia Property Investors",
      "sell_date": "2026-01-08",
      "sell_price": 368233.0,
      "seller": "Georgia Property Investors",
      "hold_days": 62,
      "profit": 134487.0,
      "roi": 57.53553001976505,
      "county": "Atkinson County"
    },
    {
      "property_id": "ATK000008",
      "address": "8569 Elm Dr, Atkinson, GA 30026",
      "buy_date": "2025-10-07",
      "buy_price": 208882.0,
      "buyer": "Georgia Home Solutions",
      "sell_date": "2025-11-28",
      "sell_price": 339726.0,
      "seller": "Georgia Home Solutions",
      "hold_days": 52,
      "profit": 130844.0,
      "roi": 62.64015089859346,
      "county": "Atkinson County"
    },
    {
      "property_id": "ATK000009",
      "address": "9861 Barrett St, Atkinson, GA 30029",
      "buy_date": "2025-11-06",
      "buy_price": 100540.0,
      "buyer": "Capital Flip Group",
      "sell_date": "2026-01-05",
      "sell_price": 208746.0,
      "seller": "Capital Flip Group",
      "hold_days": 60,
      "profit": 108206.0,
      "roi": 107.62482593992442,
      "county": "Atkinson County"
    },
    {
      "property_id": "BAC000011",
      "address": "6992 Maple Pkwy, Bacon, GA 30040",
      "buy_date": "2025-10-19",
      "buy_price": 155338.0,
      "buyer": "Georgia Renovation Group",
      "sell_date": "2026-01-24",
      "sell_price": 272139.0,
      "seller": "Georgia Renovation Group",
      "hold_days": 97,
      "profit": 116801.0,
      "roi": 75.19151785139502,
      "county": "Bacon County"
    },
    {
      "property_id": "BAC000012",
      "address": "5995 Lincoln St, Bacon, GA 30064",
      "buy_date": "2025-10-24",
      "buy_price": 240965.0,
      "buyer": "Residential Ventures",
      "sell_date": "2025-11-24",
      "sell_price": 356285.0,
      "seller": "Residential Ventures",
      "hold_days": 31,
      "profit": 115320.0,
      "roi": 47.857572676529784,
      "county": "Bacon County"
    },
    {
      "property_id": "BAK000008",
      "address": "8355 Broad St, Baker, GA 30075",
      "buy_date": "2025-10-05",
      "buy_price": 235186.0,
      "buyer": "Atlanta Capital Partners",
      "sell_date": "2026-01-18",
      "sell_price": 339063.0,
      "seller": "Atlanta Capital Partners",
      "hold_days": 105,
      "profit": 103877.0,
      "roi": 44.16802020528433,
      "county": "Baker County"
    },
    {
      "property_id": "BAK000013",
      "address": "3600 Jefferson Way, Baker, GA 30059",
      "buy_date": "2025-09-28",
      "buy_price": 183358.0,
      "buyer": "Georgia Home Solutions",
      "sell_date": "2026-02-11",
      "sell_price": 329640.0,
      "seller": "Georgia Home Solutions",
      "hold_days": 136,
      "profit": 146282.0,
      "roi": 79.77944785610663,
      "county": "Baker County"
    },
    {
      "property_id": "BAL000004",
      "address": "630 Market Pkwy, Baldwin, GA 30086",
      "buy_date": "2025-09-27",
      "buy_price": 128061.0,
      "buyer": "Investor Collective",
      "sell_date": "2025-11-19",
      "sell_price": 230845.0,
      "seller": "Investor Collective",
      "hold_days": 53,
      "profit": 102784.0,
      "roi": 80.26175025964189,
      "county": "Baldwin County"
    },
    {
      "property_id": "BAL000009",
      "address": "4686 Sugarloaf Pkwy, Baldwin, GA 30054",
      "buy_date": "2025-10-09",
      "buy_price": 143586.0,
      "buyer": "Metro Flip Team",
      "sell_date": "2025-12-26",
      "sell_price": 278109.0,
      "seller": "Metro Flip Team",
      "hold_days": 78,
      "profit": 134523.0,
      "roi": 93.68810329697881,
      "county": "Baldwin County"
    },
    {
      "property_id": "BAL000013",
      "address": "3934 Peachtree St, Baldwin, GA 30061",
      "buy_date": "2025-09-24",
      "buy_price": 213920.0,
      "buyer": "Property Solutions GA",
      "sell_date": "2025-11-18",
      "sell_price": 293370.0,
      "seller": "Property Solutions GA",
      "hold_days": 55,
      "profit": 79450.0,
      "roi": 37.140052356020945,
      "county": "Baldwin County"
    },
    {
      "property_id": "BAN000011",
      "address": "5867 Peachtree Way, Banks, GA 30059",
      "buy_date": "2025-10-20",
      "buy_price": 178612.0,
      "buyer": "Peachtree RE Group",
      "sell_date": "2025-12-21",
      "sell_price": 277730.0,
      "seller": "Peachtree RE Group",
      "hold_days": 62,
      "profit": 99118.0,
      "roi": 55.493471883188136,
      "county": "Banks County"
    },
    {
      "property_id": "BAN000019",
      "address": "8453 Lincoln Dr, Banks, GA 30056",
      "buy_date": "2025-10-08",
      "buy_price": 174573.0,
      "buyer": "Peach State Investments",
      "sell_date": "2026-01-25",
      "sell_price": 300937.0,
      "seller": "Peach State Investments",
      "hold_days": 109,
      "profit": 126364.0,
      "roi": 72.38461846906452,
      "county": "Banks County"
    },
    {
      "property_id": "BAR000000",
      "address": "4735 Elm Pkwy, Bartow, GA 30023",
      "buy_date": "2025-11-12",
      "buy_price": 180050.0,
      "buyer": "Investor Collective",
      "sell_date": "2026-02-02",
      "sell_price": 283423.0,
      "seller": "Investor Collective",
      "hold_days": 82,
      "profit": 103373.0,
      "roi": 57.41349625104137,
      "county": "Bartow County"
    },
    {
      "property_id": "BAR000011",
      "address": "8377 Memorial Ln, Barrow, GA 30072",
      "buy_date": "2025-11-23",
      "buy_price": 171222.0,
      "buyer": "Southern Holdings Inc",
      "sell_date": "2026-01-24",
      "sell_price": 278690.0,
      "seller": "Southern Holdings Inc",
      "hold_days": 62,
      "profit": 107468.0,
      "roi": 62.76529885178307,
      "county": "Barrow County"
    },
    {
      "property_id": "BAR000016",
      "address": "7883 Broad Ave, Bartow, GA 30073",
      "buy_date": "2025-09-26",
      "buy_price": 178956.0,
      "buyer": "Georgia Home Solutions",
      "sell_date": "2025-12-30",
      "sell_price": 282072.0,
      "seller": "Georgia Home Solutions",
      "hold_days": 95,
      "profit": 103116.0,
      "roi": 57.620867699322744,
      "county": "Bartow County"
    },
    {
      "property_id": "BAR000017",
      "address": "4484 Market Ave, Bartow, GA 30050",
      "buy_date": "2025-12-24",
      "buy_price": 82069.0,
      "buyer": "Renovation Experts",
      "sell_date": "2026-02-11",
      "sell_price": 180311.0,
      "seller": "Renovation Experts",
      "hold_days": 49,
      "profit": 98242.0,
      "roi": 119.70658835857633,
      "county": "Bartow County"
    },
    {
      "property_id": "BAR000020",
      "address": "5173 Barrett St, Barrow, GA 30020",
      "buy_date": "2025-10-16",
      "buy_price": 145515.0,
      "buyer": "Property Solutions GA",
      "sell_date": "2025-11-21",
      "sell_price": 246781.0,
      "seller": "Property Solutions GA",
      "hold_days": 36,
      "profit": 101266.0,
      "roi": 69.59145105315602,
      "county": "Barrow County"
    },
    {
      "property_id": "BEN000006",
      "address": "9383 Cedar Ave, Ben, GA 30014",
      "buy_date": "2025-11-30",
      "buy_price": 82531.0,
      "buyer": "Peachtree RE Group",
      "sell_date": "2026-02-03",
      "sell_price": 188295.0,
      "seller": "Peachtree RE Group",
      "hold_days": 65,
      "profit": 105764.0,
      "roi": 128.15063430710885,
      "county": "Ben Hill County"
    },
    {
      "property_id": "BEN000008",
      "address": "3977 Main Rd, Ben, GA 30028",
      "buy_date": "2025-11-06",
      "buy_price": 169783.0,
      "buyer": "Property Solutions GA",
      "sell_date": "2026-01-10",
      "sell_price": 286405.0,
      "seller": "Property Solutions GA",
      "hold_days": 65,
      "profit": 116622.0,
      "roi": 68.68885577472422,
      "county": "Ben Hill County"
    },
    {
      "property_id": "BEN000012",
      "address": "3413 Cedar Rd, Ben, GA 30062",
      "buy_date": "2025-09-06",
      "buy_price": 211181.0,
      "buyer": "Urban Development LLC",
      "sell_date": "2026-02-18",
      "sell_price": 341825.0,
      "seller": "Urban Development LLC",
      "hold_days": 165,
      "profit": 130644.0,
      "roi": 61.8635199189321,
      "county": "Ben Hill County"
    },
    {
      "property_id": "BEN000013",
      "address": "7783 Market Rd, Ben, GA 30022",
      "buy_date": "2025-12-06",
      "buy_price": 160372.0,
      "buyer": "Atlanta Flip Masters LLC",
      "sell_date": "2026-02-13",
      "sell_price": 256282.0,
      "seller": "Atlanta Flip Masters LLC",
      "hold_days": 69,
      "profit": 95910.0,
      "roi": 59.80470406305341,
      "county": "Ben Hill County"
    },
    {
      "property_id": "BER000019",
      "address": "5634 Elm Ln, Berrien, GA 30029",
      "buy_date": "2025-10-12",
      "buy_price": 218654.0,
      "buyer": "Georgia Home Solutions",
      "sell_date": "2025-12-29",
      "sell_price": 320174.0,
      "seller": "Georgia Home Solutions",
      "hold_days": 78,
      "profit": 101520.0,
      "roi": 46.42951878310024,
      "county": "Berrien County"
    },
    {
      "property_id": "BIB000001",
      "address": "428 Sugarloaf Pkwy, Bibb, GA 30043",
      "buy_date": "2025-10-18",
      "buy_price": 238023.0,
      "buyer": "Renovation Experts",
      "sell_date": "2026-01-24",
      "sell_price": 330794.0,
      "seller": "Renovation Experts",
      "hold_days": 98,
      "profit": 92771.0,
      "roi": 38.975645210756944,
      "county": "Bibb County"
    },
    {
      "property_id": "BIB000002",
      "address": "7352 Oak St, Bibb, GA 30011",
      "buy_date": "2025-11-07",
      "buy_price": 247366.0,
      "buyer": "Urban Development LLC",
      "sell_date": "2026-01-01",
      "sell_price": 372533.0,
      "seller": "Urban Development LLC",
      "hold_days": 55,
      "profit": 125167.0,
      "roi": 50.59992076518196,
      "county": "Bibb County"
    },
    {
      "property_id": "BIB000003",
      "address": "1138 Peachtree Blvd, Bibb, GA 30081",
      "buy_date": "2025-12-30",
      "buy_price": 231432.0,
      "buyer": "Peach State Investments",
      "sell_date": "2026-02-06",
      "sell_price": 372321.0,
      "seller": "Peach State Investments",
      "hold_days": 38,
      "profit": 140889.0,
      "roi": 60.87706108057659,
      "county": "Bibb County"
    },
    {
      "property_id": "BIB000005",
      "address": "2602 Broad Blvd, Bibb, GA 30075",
      "buy_date": "2025-10-20",
      "buy_price": 226955.0,
      "buyer": "Urban Development LLC",
      "sell_date": "2025-12-02",
      "sell_price": 319692.0,
      "seller": "Urban Development LLC",
      "hold_days": 43,
      "profit": 92737.0,
      "roi": 40.8614042431319,
      "county": "Bibb County"
    },
    {
      "property_id": "BIB000010",
      "address": "1553 Pine Blvd, Bibb, GA 30026",
      "buy_date": "2025-09-09",
      "buy_price": 100406.0,
      "buyer": "Investor Collective",
      "sell_date": "2026-01-13",
      "sell_price": 230778.0,
      "seller": "Investor Collective",
      "hold_days": 126,
      "profit": 130372.0,
      "roi": 129.84482999023962,
      "county": "Bibb County"
    },
    {
      "property_id": "BLE000001",
      "address": "1581 Oak Way, Bleckley, GA 30046",
      "buy_date": "2025-09-29",
      "buy_price": 135920.0,
      "buyer": "Renovation Experts",
      "sell_date": "2025-12-22",
      "sell_price": 210719.0,
      "seller": "Renovation Experts",
      "hold_days": 84,
      "profit": 74799.0,
      "roi": 55.03163625662154,
      "county": "Bleckley County"
    },
    {
      "property_id": "BLE000005",
      "address": "1791 Lincoln Ave, Bleckley, GA 30087",
      "buy_date": "2025-10-09",
      "buy_price": 176518.0,
      "buyer": "Atlanta Flip Masters LLC",
      "sell_date": "2026-01-07",
      "sell_price": 292359.0,
      "seller": "Atlanta Flip Masters LLC",
      "hold_days": 90,
      "profit": 115841.0,
      "roi": 65.62560192161706,
      "county": "Bleckley County"
    },
    {
      "property_id": "BLE000014",
      "address": "4448 Sugarloaf Ave, Bleckley, GA 30061",
      "buy_date": "2025-09-06",
      "buy_price": 223027.0,
      "buyer": "Investor Collective",
      "sell_date": "2026-02-06",
      "sell_price": 342130.0,
      "seller": "Investor Collective",
      "hold_days": 153,
      "profit": 119103.0,
      "roi": 53.402951212185066,
      "county": "Bleckley County"
    },
    {
      "property_id": "BLE000016",
      "address": "7275 Washington Way, Bleckley, GA 30098",
      "buy_date": "2025-08-29",
      "buy_price": 116631.0,
      "buyer": "Georgia Home Solutions",
      "sell_date": "2026-02-13",
      "sell_price": 253079.0,
      "seller": "Georgia Home Solutions",
      "hold_days": 168,
      "profit": 136448.0,
      "roi": 116.99119445087499,
      "county": "Bleckley County"
    },
    {
      "property_id": "BRA000004",
      "address": "9893 Main St, Brantley, GA 30062",
      "buy_date": "2025-11-18",
      "buy_price": 179353.0,
      "buyer": "Capital Flip Group",
      "sell_date": "2025-12-22",
      "sell_price": 309795.0,
      "seller": "Capital Flip Group",
      "hold_days": 34,
      "profit": 130442.0,
      "roi": 72.72919884250612,
      "county": "Brantley County"
    },
    {
      "property_id": "BRA000008",
      "address": "6865 Sugarloaf Ln, Brantley, GA 30054",
      "buy_date": "2025-10-02",
      "buy_price": 117647.0,
      "buyer": "Renovation Experts",
      "sell_date": "2026-02-03",
      "sell_price": 265692.0,
      "seller": "Renovation Experts",
      "hold_days": 124,
      "profit": 148045.0,
      "roi": 125.83831291915646,
      "county": "Brantley County"
    },
    {
      "property_id": "BRO000008",
      "address": "1754 Sugarloaf Ave, Brooks, GA 30048",
      "buy_date": "2025-10-30",
      "buy_price": 175596.0,
      "buyer": "Residential Ventures",
      "sell_date": "2025-11-30",
      "sell_price": 304465.0,
      "seller": "Residential Ventures",
      "hold_days": 31,
      "profit": 128869.0,
      "roi": 73.38948495409919,
      "county": "Brooks County"
    },
    {
      "property_id": "BRO000010",
      "address": "3776 Oak Way, Brooks, GA 30061",
      "buy_date": "2025-09-03",
      "buy_price": 219867.0,
      "buyer": "Property Solutions GA",
      "sell_date": "2025-10-17",
      "sell_price": 312490.0,
      "seller": "Property Solutions GA",
      "hold_days": 44,
      "profit": 92623.0,
      "roi": 42.12683122069251,
      "county": "Brooks County"
    },
    {
      "property_id": "BRO000014",
      "address": "2181 Memorial Dr, Brooks, GA 30057",
      "buy_date": "2025-11-22",
      "buy_price": 210798.0,
      "buyer": "Peachtree RE Group",
      "sell_date": "2026-02-20",
      "sell_price": 286347.0,
      "seller": "Peachtree RE Group",
      "hold_days": 90,
      "profit": 75549.0,
      "roi": 35.83952409415649,
      "county": "Brooks County"
    },
    {
      "property_id": "BRY000004",
      "address": "1058 Pine Dr, Bryan, GA 30039",
      "buy_date": "2025-11-11",
      "buy_price": 147643.0,
      "buyer": "Fix & Flip GA",
      "sell_date": "2025-12-18",
      "sell_price": 281202.0,
      "seller": "Fix & Flip GA",
      "hold_days": 37,
      "profit": 133559.0,
      "roi": 90.46077362286054,
      "county": "Bryan County"
    },
    {
      "property_id": "BRY000005",
      "address": "7174 Maple Dr, Bryan, GA 30016",
      "buy_date": "2025-11-09",
      "buy_price": 125665.0,
      "buyer": "Southern Holdings Inc",
      "sell_date": "2026-01-22",
      "sell_price": 248940.0,
      "seller": "Southern Holdings Inc",
      "hold_days": 74,
      "profit": 123275.0,
      "roi": 98.09811801217523,
      "county": "Bryan County"
    },
    {
      "property_id": "BRY000006",
      "address": "8537 Peachtree St, Bryan, GA 30079",
      "buy_date": "2025-12-06",
      "buy_price": 246137.0,
      "buyer": "Georgia Home Solutions",
      "sell_date": "2026-01-20",
      "sell_price": 387337.0,
      "seller": "Georgia Home Solutions",
      "hold_days": 45,
      "profit": 141200.0,
      "roi": 57.366426014780394,
      "county": "Bryan County"
    },
    {
      "property_id": "BRY000008",
      "address": "9328 Memorial Pkwy, Bryan, GA 30056",
      "buy_date": "2025-11-26",
      "buy_price": 174577.0,
      "buyer": "Georgia Property Investors",
      "sell_date": "2026-02-20",
      "sell_price": 322979.0,
      "seller": "Georgia Property Investors",
      "hold_days": 86,
      "profit": 148402.0,
      "roi": 85.00661599179732,
      "county": "Bryan County"
    },
    {
      "property_id": "BRY000010",
      "address": "9059 Elm Pkwy, Bryan, GA 30031",
      "buy_date": "2025-10-04",
      "buy_price": 112793.0,
      "buyer": "Atlanta Capital Partners",
      "sell_date": "2026-02-22",
      "sell_price": 184052.0,
      "seller": "Atlanta Capital Partners",
      "hold_days": 141,
      "profit": 71259.0,
      "roi": 63.176792886083355,
      "county": "Bryan County"
    },
    {
      "property_id": "BRY000016",
      "address": "4763 Barrett Blvd, Bryan, GA 30071",
      "buy_date": "2025-10-08",
      "buy_price": 166485.0,
      "buyer": "Peach State Investments",
      "sell_date": "2026-01-22",
      "sell_price": 245645.0,
      "seller": "Peach State Investments",
      "hold_days": 106,
      "profit": 79160.0,
      "roi": 47.54782713157341,
      "county": "Bryan County"
    },
    {
      "property_id": "BUL000001",
      "address": "8404 Broad Dr, Bulloch, GA 30054",
      "buy_date": "2025-08-29",
      "buy_price": 183857.0,
      "buyer": "Renovation Experts",
      "sell_date": "2025-10-13",
      "sell_price": 322898.0,
      "seller": "Renovation Experts",
      "hold_days": 45,
      "profit": 139041.0,
      "roi": 75.62453428479743,
      "county": "Bulloch County"
    },
    {
      "property_id": "BUL000019",
      "address": "7135 Peachtree Rd, Bulloch, GA 30048",
      "buy_date": "2025-10-18",
      "buy_price": 127541.0,
      "buyer": "Fix & Flip GA",
      "sell_date": "2026-02-17",
      "sell_price": 272692.0,
      "seller": "Fix & Flip GA",
      "hold_days": 122,
      "profit": 145151.0,
      "roi": 113.80732470342869,
      "county": "Bulloch County"
    },
    {
      "property_id": "BUL000021",
      "address": "917 Elm Blvd, Bulloch, GA 30081",
      "buy_date": "2025-10-22",
      "buy_price": 243624.0,
      "buyer": "Quick Turn Properties",
      "sell_date": "2026-01-24",
      "sell_price": 363751.0,
      "seller": "Quick Turn Properties",
      "hold_days": 94,
      "profit": 120127.0,
      "roi": 49.308360424260336,
      "county": "Bulloch County"
    }
  ],
  "stats": {
    "total_flips_identified": 357,
    "total_investors": 18,
    "total_profit": 40807044.0,
    "avg_roi": 75.52652469450443,
    "last_updated": "2026-02-24",
    "by_county": {
      "Elbert County": 7,
      "Bryan County": 6,
      "Madison County": 6,
      "Telfair County": 6,
      "Towns County": 6,
      "Bibb County": 5,
      "Early County": 5,
      "Echols County": 5,
      "Long County": 5,
      "Taliaferro County": 5,
      "Appling County": 4,
      "Atkinson County": 4,
      "Ben Hill County": 4,
      "Bleckley County": 4,
      "Columbia County": 4,
      "Crisp County": 4,
      "Dougherty County": 4,
      "Douglas County": 4,
      "Fulton County": 4,
      "Glynn County": 4,
      "Hancock County": 4,
      "Houston County": 4,
      "Johnson County": 4,
      "McIntosh County": 4,
      "Meriwether County": 4,
      "Murray County": 4,
      "Quitman County": 4,
      "Stewart County": 4,
      "Tattnall County": 4,
      "Terrell County": 4,
      "Twiggs County": 4,
      "Baldwin County": 3,
      "Bartow County": 3,
      "Brooks County": 3,
      "Bulloch County": 3,
      "Butts County": 3,
      "Carroll County": 3,
      "Chattooga County": 3,
      "Cook County": 3,
      "Coweta County": 3,
      "Effingham County": 3,
      "Fayette County": 3,
      "Glascock County": 3,
      "Greene County": 3,
      "Irwin County": 3,
      "Jasper County": 3,
      "Lee County": 3,
      "Liberty County": 3,
      "McDuffie County": 3,
      "Monroe County": 3,
      "Morgan County": 3,
      "Newton County": 3,
      "Putnam County": 3,
      "Randolph County": 3,
      "Rockdale County": 3,
      "Spalding County": 3,
      "Talbot County": 3,
      "Turner County": 3,
      "Upson County": 3,
      "Walton County": 3,
      "Wayne County": 3,
      "Webster County": 3,
      "Wilkinson County": 3,
      "Bacon County": 2,
      "Baker County": 2,
      "Banks County": 2,
      "Barrow County": 2,
      "Brantley County": 2,
      "Calhoun County": 2,
      "Camden County": 2,
      "Candler County": 2,
      "Chatham County": 2,
      "Clayton County": 2,
      "Clay County": 2,
      "Crawford County": 2,
      "Dawson County": 2,
      "Decatur County": 2,
      "DeKalb County": 2,
      "Evans County": 2,
      "Forsyth County": 2,
      "Franklin County": 2,
      "Grady County": 2,
      "Habersham County": 2,
      "Hart County": 2,
      "Jenkins County": 2,
      "Jones County": 2,
      "Lanier County": 2,
      "Lincoln County": 2,
      "Lowndes County": 2,
      "Lumpkin County": 2,
      "Macon County": 2,
      "Muscogee County": 2,
      "Oglethorpe County": 2,
      "Paulding County": 2,
      "Peach County": 2,
      "Pike County": 2,
      "Polk County": 2,
      "Richmond County": 2,
      "Seminole County": 2,
      "Stephens County": 2,
      "Taylor County": 2,
      "Toombs County": 2,
      "Treutlen County": 2,
      "Walker County": 2,
      "Ware County": 2,
      "Warren County": 2,
      "Whitfield County": 2,
      "Worth County": 2,
      "Berrien County": 1,
      "Burke County": 1,
      "Catoosa County": 1,
      "Cherokee County": 1,
      "Clarke County": 1,
      "Clinch County": 1,
      "Coffee County": 1,
      "Dade County": 1,
      "Dooly County": 1,
      "Emanuel County": 1,
      "Floyd County": 1,
      "Gilmer County": 1,
      "Gwinnett County": 1,
      "Hall County": 1,
      "Heard County": 1,
      "Henry County": 1,
      "Jackson County": 1,
      "Jefferson County": 1,
      "Laurens County": 1,
      "Marion County": 1,
      "Mitchell County": 1,
      "Pulaski County": 1,
      "Rabun County": 1,
      "Schley County": 1,
      "Screven County": 1,
      "Sumter County": 1,
      "Thomas County": 1,
      "Troup County": 1,
      "Union County": 1,
      "Washington County": 1,
      "Wilkes County": 1
    },
    "profit_distribution": {
      "70k-100k": 95,
      "100k-130k": 166,
      "130k-160k": 96,
      "160k+": 0
    }
  }
}