{
  "timestamp": "2026-04-06T18:19:51.350793",
  "pipeline_version": "1.0.0",
  "data_summary": {
    "total_transactions": 8436,
    "unique_counties": 159,
    "date_range": {
      "min_date": "2025-10-08",
      "max_date": "2026-04-06"
    }
  },
  "flips_summary": {
    "total_flips": 380,
    "total_profit": 43881665.0,
    "avg_profit": 115478.06578947368,
    "avg_hold_days": 78.24736842105263
  },
  "investors_summary": {
    "total_investors": 18,
    "top_5_investors": [
      {
        "investor_name": "Peach State Investments",
        "total_flips": 28,
        "total_profit": 3263342.0,
        "avg_profit_per_flip": 116547.92857142857,
        "avg_hold_days": 73.89285714285714,
        "avg_roi": 100.0
      },
      {
        "investor_name": "Atlanta Capital Partners",
        "total_flips": 26,
        "total_profit": 2999644.0,
        "avg_profit_per_flip": 115370.92307692308,
        "avg_hold_days": 86.1923076923077,
        "avg_roi": 100.0
      },
      {
        "investor_name": "Property Solutions GA",
        "total_flips": 26,
        "total_profit": 2850207.0,
        "avg_profit_per_flip": 109623.34615384616,
        "avg_hold_days": 77.57692307692308,
        "avg_roi": 100.0
      },
      {
        "investor_name": "Georgia Home Solutions",
        "total_flips": 25,
        "total_profit": 2903533.0,
        "avg_profit_per_flip": 116141.32,
        "avg_hold_days": 82.16,
        "avg_roi": 100.0
      },
      {
        "investor_name": "Investor Collective",
        "total_flips": 24,
        "total_profit": 2756321.0,
        "avg_profit_per_flip": 114846.70833333333,
        "avg_hold_days": 88.29166666666667,
        "avg_roi": 100.0
      }
    ]
  }
}